jaccard_precalc/JaccardPrecalc.py
jaccard_precalc/__init__.py
jaccard_precalc-0.1.6.dist-info/WHEEL
jaccard_precalc-0.1.6.dist-info/METADATA
jaccard_precalc-0.1.6.dist-info/RECORD
